argdoc.py
ArgDoc-0.1.2.dist-info/METADATA
ArgDoc-0.1.2.dist-info/RECORD
ArgDoc-0.1.2.dist-info/WHEEL
ArgDoc-0.1.2.dist-info/top_level.txt
argdoc/__init__.py
argdoc/argdoc.py
argdoc/version.py
